schema_induction/__init__.py
schema_induction/class_type.py
schema_induction/list_type.py
schema_induction/primitive_type.py
schema_induction/schema.py
schema_induction/type.py
schema_induction/union_type.py
schema_induction-1.1.7.dist-info/WHEEL
schema_induction-1.1.7.dist-info/METADATA
schema_induction-1.1.7.dist-info/RECORD
